imageComp.py
imageComp-0.1.0.dist-info/LICENSE
imageComp-0.1.0.dist-info/METADATA
imageComp-0.1.0.dist-info/WHEEL
imageComp-0.1.0.dist-info/entry_points.txt
imageComp-0.1.0.dist-info/top_level.txt
imageComp-0.1.0.dist-info/RECORD
