Metadata-Version: 2.1
Name: imageComp
Version: 0.1.0
Summary: A small example package
Home-page: https://github.com/Im-not-yoneda/image_compression
Author: Yoneda
Author-email: s2122053@stu.musashino-u.ac.jp
License: UNKNOWN
Project-URL: Bug Tracker, https://github.com/Im-not-yoneda/image_compression
Platform: UNKNOWN
Classifier: Programming Language :: Python :: 3
Classifier: License :: OSI Approved :: MIT License
Classifier: Operating System :: OS Independent
Requires-Python: >=3.6
